p360_export/ExportManager.py
p360_export/ExportRunner.py
p360_export/_config/config.yaml
p360_export/config/AzureStorageConfigGetter.py
p360_export/config/AzureStorageConfigGetterTest.py
p360_export/config/ConfigGetterInterface.py
p360_export/config/LocalFileConfigGetter.py
p360_export/config/LocalFileConfigGetterTest.py
p360_export/config/SkeletonConfigGetter.py
p360_export/containers/Container.py
p360_export/containers/ContainerTest.py
p360_export/containers/Core.py
p360_export/containers/DataPlatformContainer.py
p360_export/containers/FacebookContainer.py
p360_export/containers/GoogleAdsContainer.py
p360_export/containers/GoogleAnalytics4Container.py
p360_export/containers/SFMCContainer.py
p360_export/data/ColumnMappingGetter.py
p360_export/data/ColumnMappingGetterTest.py
p360_export/data/DataPicker.py
p360_export/data/build/DataBuilderInterface.py
p360_export/data/build/FeatureStoreDataBuilder.py
p360_export/data/build/FeatureStoreDataBuilderTest.py
p360_export/data/extra/FacebookData.py
p360_export/data/fix/DataFixerInterface.py
p360_export/data/fix/DataFixersTest.py
p360_export/data/fix/DataPlatformDataFixer.py
p360_export/data/fix/FacebookDataFixer.py
p360_export/data/fix/GoogleAdsDataFixer.py
p360_export/data/fix/GoogleAnalytics4DataFixer.py
p360_export/data/fix/SFMCDataFixer.py
p360_export/data/type/resolve/DataFrameTypeResolver.py
p360_export/data/type/resolve/SFMCTypeResolver.py
p360_export/data/type/resolve/TypeResolverInterface.py
p360_export/data/type/resolve/TypeResolversTest.py
p360_export/data/type/validate/EmailValidator.py
p360_export/data/type/validate/PhoneNumberValidator.py
p360_export/data/type/validate/ValidatorInterface.py
p360_export/data/type/validate/ValidatorsTest.py
p360_export/exceptions/config.py
p360_export/exceptions/data_picker.py
p360_export/exceptions/exporter.py
p360_export/exceptions/manager.py
p360_export/exceptions/query_builder.py
p360_export/exceptions/type_resolver.py
p360_export/exceptions/utils.py
p360_export-1.5.8.dist-info/LICENSE
p360_export-1.5.8.dist-info/WHEEL
p360_export-1.5.8.dist-info/METADATA
p360_export-1.5.8.dist-info/RECORD
