Metadata-Version: 2.1
Name: p360-export
Version: 1.5.8
Summary: Persona360 data export
License: Proprietary
Author: Datasentics
Author-email: jiri.koutny@datasentics.com
Requires-Python: >=3.8.10,<4.0.0
Classifier: License :: Other/Proprietary License
Classifier: Operating System :: OS Independent
Classifier: Programming Language :: Python :: 3
Classifier: Programming Language :: Python :: 3.10
Classifier: Programming Language :: Python :: 3.9
Requires-Dist: Salesforce-FuelSDK-Sans (>=1.3.0,<2.0.0)
Requires-Dist: dependency-injector (>=4.40.0,<5.0.0)
Requires-Dist: facebook-business (>=13.0.0,<14.0.0)
Requires-Dist: google-ads (>=16.0.0,<17.0.0)
Requires-Dist: ipython (>=8.7.0,<9.0.0)
Requires-Dist: jsonschema (>=4.4.0,<5.0.0)
Requires-Dist: pandas (>=1.5.2,<2.0.0)
Requires-Dist: paramiko (>=2.11.0,<3.0.0)
Requires-Dist: pyarrow (>=10.0.1,<11.0.0)
